MANIFEST.in
README.md
README.rst
setup.py
behave_rest/__init__.py
behave_rest/environment.py
behave_rest.egg-info/PKG-INFO
behave_rest.egg-info/SOURCES.txt
behave_rest.egg-info/dependency_links.txt
behave_rest.egg-info/pbr.json
behave_rest.egg-info/requires.txt
behave_rest.egg-info/top_level.txt
behave_rest/steps/__init__.py