Metadata-Version: 1.1
Name: behave-rest
Version: 0.1.3
Summary: BDD-style Rest API testing tool
Home-page: https://github.com/stanfy/behave-rest
Author: Oleg Nikiforov
Author-email: nikiphor@hotmail.com
License: Apache Software License
Platform: UNKNOWN
Classifier: Development Status :: 3 - Alpha
Classifier: Intended Audience :: Developers
Classifier: Topic :: Software Development :: Testing
Classifier: License :: OSI Approved :: Apache Software License
Classifier: Operating System :: OS Independent
Classifier: Programming Language :: Python
Classifier: Programming Language :: Python :: 3
